COPYING
ChangeLog
INSTALL
MANIFEST.in
NEW_IN_MACS14
README
setup.cfg
setup.py
MACS.egg-info/PKG-INFO
MACS.egg-info/SOURCES.txt
MACS.egg-info/dependency_links.txt
MACS.egg-info/top_level.txt
bin/elandexport2bed
bin/elandmulti2bed
bin/elandresult2bed
bin/macs
bin/sam2bed
bin/wignorm
lib/Constants.py
lib/OptValidator.py
lib/OutputWriter.py
lib/PeakDetect.py
lib/PeakModel.py
lib/Prob.py
lib/__init__.py
lib/IO/BinKeeper.py
lib/IO/FeatIO.py
lib/IO/Parser.py
lib/IO/WiggleIO.py
lib/IO/__init__.py
lib/IO/bedGraphIO.py