Metadata-Version: 1.1
Name: MACS
Version: 1.4.3
Summary: Model Based Analysis for ChIP-Seq data
Home-page: http://liulab.dfci.harvard.edu/MACS/
Author: Yong Zhang; Tao (Foo) Liu
Author-email: zy@jimmy.harvard.edu; taoliu@jimmy.harvard.edu
License: UNKNOWN
Platform: UNKNOWN
Classifier: Development Status :: 5 - Production/Stable
Classifier: Environment :: Console
Classifier: Intended Audience :: Developers
Classifier: License :: OSI Approved :: Artistic License
Classifier: Operating System :: MacOS :: MacOS X
Classifier: Operating System :: Microsoft :: Windows
Classifier: Operating System :: POSIX
Classifier: Programming Language :: Python
